deforum/__init__.py
deforum-0.2.1.dist-info/licenses/LICENSE
deforum-0.2.1.dist-info/METADATA
deforum-0.2.1.dist-info/WHEEL
deforum-0.2.1.dist-info/top_level.txt
deforum-0.2.1.dist-info/RECORD
